fb2cal/__init__.py
fb2cal/__main__.py
fb2cal/__meta__.py
fb2cal/config.py
fb2cal/facebook_browser.py
fb2cal/facebook_user.py
fb2cal/ics_writer.py
fb2cal/logger.py
fb2cal/transformer.py
fb2cal/utils.py
fb2cal-1.3.2.dist-info/licenses/LICENSE
fb2cal-1.3.2.dist-info/METADATA
fb2cal-1.3.2.dist-info/WHEEL
fb2cal-1.3.2.dist-info/top_level.txt
fb2cal-1.3.2.dist-info/RECORD
